ipyaggrid/__init__.py
ipyaggrid/__meta__.py
ipyaggrid/builder_params.py
ipyaggrid/community.py
ipyaggrid/display.py
ipyaggrid/grid.py
ipyaggrid/ipyaggrid.json
ipyaggrid/util.py
ipyaggrid/flexbox/__init__.py
ipyaggrid/flexbox/flexbox_css.py
ipyaggrid/flexbox/flexbox_standard.py
ipyaggrid/js/helpersBuiltin.js
ipyaggrid/labextension/package.json
ipyaggrid/labextension/static/155.744dc0f81b3c2dbd829e.js
ipyaggrid/labextension/static/486.9a102cac74aa3af2b7b8.js
ipyaggrid/labextension/static/486.9a102cac74aa3af2b7b8.js.LICENSE.txt
ipyaggrid/labextension/static/590.b222061c30cf4410a079.js
ipyaggrid/labextension/static/590.b222061c30cf4410a079.js.LICENSE.txt
ipyaggrid/labextension/static/591.89fd4c700b5e9bf9a04d.js
ipyaggrid/labextension/static/628.a876a22b5bf4766eb88f.js
ipyaggrid/labextension/static/680.9780c99311f6aacd0551.js
ipyaggrid/labextension/static/731.0e661d2646511263a3f4.js
ipyaggrid/labextension/static/731.0e661d2646511263a3f4.js.LICENSE.txt
ipyaggrid/labextension/static/906.95bbf22d029b842482b2.js
ipyaggrid/labextension/static/906.95bbf22d029b842482b2.js.LICENSE.txt
ipyaggrid/labextension/static/remoteEntry.14fafb59423303ffefaf.js
ipyaggrid/labextension/static/style.js
ipyaggrid/labextension/static/third-party-licenses.json
ipyaggrid/magics/__init__.py
ipyaggrid/magics/custom_magics.py
ipyaggrid/nbextension/906.index.js
ipyaggrid/nbextension/906.index.js.LICENSE.txt
ipyaggrid/nbextension/906.index.js.map
ipyaggrid/nbextension/extension.js
ipyaggrid/nbextension/index.js
ipyaggrid/nbextension/index.js.LICENSE.txt
ipyaggrid/nbextension/index.js.map
ipyaggrid-0.5.4.data/data/etc/jupyter/nbconfig/notebook.d/ipyaggrid.json
ipyaggrid-0.5.4.data/data/share/jupyter/labextensions/ipyaggrid/install.json
ipyaggrid-0.5.4.data/data/share/jupyter/labextensions/ipyaggrid/package.json
ipyaggrid-0.5.4.data/data/share/jupyter/labextensions/ipyaggrid/static/155.744dc0f81b3c2dbd829e.js
ipyaggrid-0.5.4.dist-info/LICENSE
ipyaggrid-0.5.4.dist-info/METADATA
ipyaggrid-0.5.4.dist-info/WHEEL
ipyaggrid-0.5.4.dist-info/top_level.txt
ipyaggrid-0.5.4.dist-info/RECORD
