Metadata-Version: 2.1
Name: ipyaggrid
Version: 0.5.4
Summary: Jupyter widget - ag-grid in the notebook
Home-page: https://github.com/widgetti/ipyaggrid
Author: Mario Buikhuizen, Maarten Breddels, DGothrek
Author-email: mariobuikhuizen@gmail.com, maartenbreddels@gmail.com
License: MIT
Download-URL: https://github.com/widgetti/ipyaggrid/archive/refs/tags/v0.5.4.zip
Keywords: ipywidget,javascript,ag-grid
Platform: UNKNOWN
Classifier: Development Status :: 4 - Beta
Classifier: License :: OSI Approved :: MIT License
Classifier: Programming Language :: Python :: 3.5
Classifier: Programming Language :: Python :: 3.6
Requires-Dist: ipywidgets >=7.4.0
Requires-Dist: pandas
Requires-Dist: simplejson >=3.13.2
Provides-Extra: ui-test
Requires-Dist: solara[pytest] ; extra == 'ui-test'
Requires-Dist: jupyter-server <2 ; extra == 'ui-test'
Requires-Dist: playwright ==1.32.1 ; extra == 'ui-test'
Requires-Dist: jupyterlab ==3.6.3 ; extra == 'ui-test'
Provides-Extra: unit-test
Requires-Dist: pytest ; extra == 'unit-test'
